{
  "name": 1300067,
  "SubTexture": [
    {
      "name": "元件 1",
      "x": 499,
      "width": 5,
      "y": 136,
      "height": 4
    },
    {
      "name": "补间 1",
      "x": 394,
      "width": 103,
      "y": 136,
      "height": 121
    },
    {
      "name": "补间 2",
      "x": 196,
      "width": 110,
      "y": 329,
      "height": 95
    },
    {
      "name": "补间 3",
      "x": 0,
      "width": 112,
      "y": 322,
      "height": 97
    },
    {
      "name": "补间 4",
      "x": 394,
      "width": 114,
      "y": 0,
      "height": 134
    },
    {
      "name": "元件 3",
      "x": 0,
      "width": 205,
      "y": 0,
      "height": 196
    },
    {
      "name": "元件 4",
      "x": 397,
      "width": 74,
      "y": 373,
      "height": 77
    },
    {
      "name": "元件 5",
      "x": 207,
      "width": 185,
      "y": 0,
      "height": 163
    },
    {
      "name": "补间 6",
      "x": 114,
      "width": 80,
      "y": 322,
      "height": 81
    },
    {
      "name": "io018",
      "x": 0,
      "width": 191,
      "y": 198,
      "height": 122
    },
    {
      "name": "补间 9",
      "x": 308,
      "width": 87,
      "y": 373,
      "height": 69
    },
    {
      "name": "元件 13",
      "x": 207,
      "width": 159,
      "y": 165,
      "height": 162
    },
    {
      "name": "元件 17",
      "x": 368,
      "width": 129,
      "y": 259,
      "height": 112
    }
  ],
  "imagePath": "1300067_tex.png"
}