{
  "resources": [
    {
      "type": "json",
      "url": "1373.json",
      "name": "road_1373"
    },
    {
      "type": "text",
      "url": "Map1373Skin.exml",
      "name": "exml_1373"
    },
    {
      "type": "image",
      "url": "map_1373_bg_mc.jpg",
      "name": "map_1373_bg_mc_jpg"
    },
    {
      "type": "image",
      "url": "map_1373_top_mc.png",
      "name": "map_1373_top_mc_png"
    }
  ],
  "groups": [
    {
      "keys": "road_1373,exml_1373,map_1373_bg_mc_jpg,map_1373_top_mc_png",
      "name": "map_1373"
    }
  ]
}